odoo/addons/iot_output_oca/README.rst
odoo/addons/iot_output_oca/__init__.py
odoo/addons/iot_output_oca/__manifest__.py
odoo/addons/iot_output_oca/i18n/es.po
odoo/addons/iot_output_oca/i18n/fa.po
odoo/addons/iot_output_oca/i18n/iot_output.pot
odoo/addons/iot_output_oca/i18n/iot_output_oca.pot
odoo/addons/iot_output_oca/i18n/it.po
odoo/addons/iot_output_oca/models/__init__.py
odoo/addons/iot_output_oca/models/iot_communication_system.py
odoo/addons/iot_output_oca/models/iot_device.py
odoo/addons/iot_output_oca/models/iot_device_output.py
odoo/addons/iot_output_oca/models/iot_device_output_action.py
odoo/addons/iot_output_oca/readme/CONTRIBUTORS.md
odoo/addons/iot_output_oca/readme/DESCRIPTION.md
odoo/addons/iot_output_oca/security/ir.model.access.csv
odoo/addons/iot_output_oca/static/description/icon.png
odoo/addons/iot_output_oca/static/description/index.html
odoo/addons/iot_output_oca/tests/__init__.py
odoo/addons/iot_output_oca/tests/test_iot.py
odoo/addons/iot_output_oca/views/iot_device_output_views.xml
odoo/addons/iot_output_oca/views/iot_device_views.xml
odoo_addon_iot_output_oca-17.0.1.0.0.3.dist-info/METADATA
odoo_addon_iot_output_oca-17.0.1.0.0.3.dist-info/WHEEL
odoo_addon_iot_output_oca-17.0.1.0.0.3.dist-info/top_level.txt
odoo_addon_iot_output_oca-17.0.1.0.0.3.dist-info/RECORD
